mkdocs_cluster/404.html
mkdocs_cluster/__init__.py
mkdocs_cluster/content.html
mkdocs_cluster/main.html
mkdocs_cluster/mkdocs_theme.yml
mkdocs_cluster/nav.html
mkdocs_cluster/toc.html
mkdocs_cluster/css/base.css
mkdocs_cluster/css/bootstrap.min.css
mkdocs_cluster/css/font-awesome.min.css
mkdocs_cluster/css/highlight.min.css
mkdocs_cluster/fonts/fontawesome-webfont.eot
mkdocs_cluster/fonts/fontawesome-webfont.svg
mkdocs_cluster/fonts/fontawesome-webfont.ttf
mkdocs_cluster/fonts/fontawesome-webfont.woff
mkdocs_cluster/fonts/fontawesome-webfont.woff2
mkdocs_cluster/fonts/glyphicons-halflings-regular.eot
mkdocs_cluster/fonts/glyphicons-halflings-regular.svg
mkdocs_cluster/fonts/glyphicons-halflings-regular.ttf
mkdocs_cluster/fonts/glyphicons-halflings-regular.woff
mkdocs_cluster/fonts/glyphicons-halflings-regular.woff2
mkdocs_cluster/img/favicon.ico
mkdocs_cluster/js/base.js
mkdocs_cluster/js/bootstrap.min.js
mkdocs_cluster/js/highlight.min.js
mkdocs_cluster/js/jquery.min.js
mkdocs_cluster-0.0.9.dist-info/DESCRIPTION.rst
mkdocs_cluster-0.0.9.dist-info/METADATA
mkdocs_cluster-0.0.9.dist-info/RECORD
mkdocs_cluster-0.0.9.dist-info/WHEEL
mkdocs_cluster-0.0.9.dist-info/entry_points.txt
mkdocs_cluster-0.0.9.dist-info/metadata.json
mkdocs_cluster-0.0.9.dist-info/top_level.txt
