Metadata-Version: 2.0
Name: mkdocs-cluster
Version: 0.0.9
Summary: Another bootstrap theme for MkDocs
Home-page: https://gitlab.com/kaliko/mkdocs-cluster
Author: kaliko jack
Author-email: kaliko@azylum.org
License: BSD
Platform: UNKNOWN
Classifier: Development Status :: 5 - Production/Stable
Classifier: License :: OSI Approved :: BSD License
Classifier: Programming Language :: Python :: 2
Classifier: Programming Language :: Python :: 2.6
Classifier: Programming Language :: Python :: 2.7
Classifier: Programming Language :: Python :: 3
Classifier: Programming Language :: Python :: 3.2
Classifier: Programming Language :: Python :: 3.3
Classifier: Programming Language :: Python :: 3.4
Classifier: Programming Language :: Python :: 3.5
Requires-Dist: mkdocs (>=1.0.0)
